odoo10_addon_hr_payroll_account_operating_unit-10.0.1.0.1-py3.6-nspkg.pth
odoo/addons/hr_payroll_account_operating_unit/README.rst
odoo/addons/hr_payroll_account_operating_unit/__init__.py
odoo/addons/hr_payroll_account_operating_unit/__manifest__.py
odoo/addons/hr_payroll_account_operating_unit/models/__init__.py
odoo/addons/hr_payroll_account_operating_unit/models/account_move.py
odoo/addons/hr_payroll_account_operating_unit/models/hr_payslip.py
odoo/addons/hr_payroll_account_operating_unit/static/description/icon.png
odoo/addons/hr_payroll_account_operating_unit/tests/__init__.py
odoo/addons/hr_payroll_account_operating_unit/tests/test_payroll_account_operating_unit.py
odoo10_addon_hr_payroll_account_operating_unit-10.0.1.0.1.dist-info/METADATA
odoo10_addon_hr_payroll_account_operating_unit-10.0.1.0.1.dist-info/WHEEL
odoo10_addon_hr_payroll_account_operating_unit-10.0.1.0.1.dist-info/namespace_packages.txt
odoo10_addon_hr_payroll_account_operating_unit-10.0.1.0.1.dist-info/top_level.txt
odoo10_addon_hr_payroll_account_operating_unit-10.0.1.0.1.dist-info/RECORD
